README.md
setup.py
buyuan.egg-info/PKG-INFO
buyuan.egg-info/SOURCES.txt
buyuan.egg-info/dependency_links.txt
buyuan.egg-info/top_level.txt
spider/__init__.py
spider/tools.py