Metadata-Version: 2.1
Name: buyuan
Version: 0.0.2
Summary: buyuan tools
Home-page: UNKNOWN
Author: seal
Author-email: seal7108@gmail.com
License: UNKNOWN
Platform: UNKNOWN
Classifier: Programming Language :: Python :: 2
Classifier: License :: OSI Approved :: MIT License
Classifier: Operating System :: OS Independent
Requires-Python: >=2.7
